{
  "status": "ok",
  "source_name": "e_series_etf_tail_risk_policy_walk_forward",
  "strategy_model_code": "E-ETF-V01",
  "sleeve_model_code": "AI-E-ETF-SLEEVE-SELECTION-V01",
  "as_of_date": "2026-05-13",
  "generated_at": "2026-05-14T18:42:19",
  "valid_start": "2024-01-01",
  "lookback_days": 365,
  "label_lag_days": 31,
  "min_segment_rows": 24,
  "candidate_policies": {
    "baseline_top3_role": {
      "score_col": "e_baseline_selection_score",
      "top_n": 3,
      "label": "Baseline rule Top3 per role"
    },
    "ai_top3_role": {
      "score_col": "sleeve_selection_prob",
      "top_n": 3,
      "label": "AI Top3 per role"
    },
    "hybrid_b70_ai30_top3_role": {
      "score_col": "e_hybrid_b70_ai30_score",
      "top_n": 3,
      "label": "Hybrid baseline 70% + AI 30% Top3 per role"
    },
    "hybrid_b50_ai50_top3_role": {
      "score_col": "e_hybrid_b50_ai50_score",
      "top_n": 3,
      "label": "Hybrid baseline 50% + AI 50% Top3 per role"
    },
    "ai_quality_guard_top3_role": {
      "score_col": "e_ai_quality_guard_score",
      "top_n": 3,
      "label": "AI + quality/risk guard Top3 per role"
    }
  },
  "tail_score_weights": {
    "worst_1m_ret": 0.35,
    "avg_1m_mdd": 0.25,
    "avg_1m_risk_adj": 0.25,
    "win_rate": 0.1,
    "avg_1m_ret": 0.05
  },
  "evaluated_dates": 26,
  "best_portfolio_policy": [
    {
      "policy": "wf_tail_asset_policy",
      "periods": 26,
      "priced_periods": 26,
      "avg_1m_ret": 0.020433,
      "median_1m_ret": 0.007076,
      "win_rate": 0.576923,
      "avg_1m_risk_adj": 0.00593,
      "avg_1m_mdd_proxy": -0.029005,
      "worst_1m_ret": -0.03164,
      "compounded_validation_return": 0.646032,
      "baseline_avg_1m_ret": 0.018259,
      "avg_1m_ret_delta": 0.002173999999999999,
      "baseline_win_rate": 0.576923,
      "win_rate_delta": 0.0,
      "baseline_avg_1m_risk_adj": 0.002327,
      "avg_1m_risk_adj_delta": 0.0036030000000000003,
      "baseline_avg_1m_mdd_proxy": -0.031865,
      "avg_1m_mdd_proxy_delta": 0.002859999999999998,
      "baseline_worst_1m_ret": -0.076366,
      "worst_1m_ret_delta": 0.044726,
      "baseline_compounded_validation_return": 0.54758,
      "compounded_validation_return_delta": 0.0984520000000001
    }
  ],
  "portfolio_summary": [
    {
      "policy": "wf_tail_asset_policy",
      "periods": 26,
      "priced_periods": 26,
      "avg_1m_ret": 0.020433,
      "median_1m_ret": 0.007076,
      "win_rate": 0.576923,
      "avg_1m_risk_adj": 0.00593,
      "avg_1m_mdd_proxy": -0.029005,
      "worst_1m_ret": -0.03164,
      "compounded_validation_return": 0.646032,
      "baseline_avg_1m_ret": 0.018259,
      "avg_1m_ret_delta": 0.002173999999999999,
      "baseline_win_rate": 0.576923,
      "win_rate_delta": 0.0,
      "baseline_avg_1m_risk_adj": 0.002327,
      "avg_1m_risk_adj_delta": 0.0036030000000000003,
      "baseline_avg_1m_mdd_proxy": -0.031865,
      "avg_1m_mdd_proxy_delta": 0.002859999999999998,
      "baseline_worst_1m_ret": -0.076366,
      "worst_1m_ret_delta": 0.044726,
      "baseline_compounded_validation_return": 0.54758,
      "compounded_validation_return_delta": 0.0984520000000001
    },
    {
      "policy": "hybrid_b50_ai50_top3_role",
      "periods": 26,
      "priced_periods": 26,
      "avg_1m_ret": 0.021174,
      "median_1m_ret": 0.009331,
      "win_rate": 0.576923,
      "avg_1m_risk_adj": 0.004684,
      "avg_1m_mdd_proxy": -0.032981,
      "worst_1m_ret": -0.07498,
      "compounded_validation_return": 0.6562,
      "baseline_avg_1m_ret": 0.018259,
      "avg_1m_ret_delta": 0.0029149999999999975,
      "baseline_win_rate": 0.576923,
      "win_rate_delta": 0.0,
      "baseline_avg_1m_risk_adj": 0.002327,
      "avg_1m_risk_adj_delta": 0.0023569999999999997,
      "baseline_avg_1m_mdd_proxy": -0.031865,
      "avg_1m_mdd_proxy_delta": -0.0011160000000000059,
      "baseline_worst_1m_ret": -0.076366,
      "worst_1m_ret_delta": 0.0013859999999999983,
      "baseline_compounded_validation_return": 0.54758,
      "compounded_validation_return_delta": 0.10862000000000005
    },
    {
      "policy": "ai_quality_guard_top3_role",
      "periods": 26,
      "priced_periods": 26,
      "avg_1m_ret": 0.018121,
      "median_1m_ret": 0.011557,
      "win_rate": 0.615385,
      "avg_1m_risk_adj": 0.003811,
      "avg_1m_mdd_proxy": -0.028622,
      "worst_1m_ret": -0.027661,
      "compounded_validation_return": 0.565243,
      "baseline_avg_1m_ret": 0.018259,
      "avg_1m_ret_delta": -0.00013799999999999923,
      "baseline_win_rate": 0.576923,
      "win_rate_delta": 0.038461999999999996,
      "baseline_avg_1m_risk_adj": 0.002327,
      "avg_1m_risk_adj_delta": 0.001484,
      "baseline_avg_1m_mdd_proxy": -0.031865,
      "avg_1m_mdd_proxy_delta": 0.003242999999999996,
      "baseline_worst_1m_ret": -0.076366,
      "worst_1m_ret_delta": 0.048705,
      "baseline_compounded_validation_return": 0.54758,
      "compounded_validation_return_delta": 0.017663000000000095
    },
    {
      "policy": "hybrid_b70_ai30_top3_role",
      "periods": 26,
      "priced_periods": 26,
      "avg_1m_ret": 0.020158,
      "median_1m_ret": 0.005669,
      "win_rate": 0.576923,
      "avg_1m_risk_adj": 0.003799,
      "avg_1m_mdd_proxy": -0.032718,
      "worst_1m_ret": -0.074835,
      "compounded_validation_return": 0.615646,
      "baseline_avg_1m_ret": 0.018259,
      "avg_1m_ret_delta": 0.001898999999999998,
      "baseline_win_rate": 0.576923,
      "win_rate_delta": 0.0,
      "baseline_avg_1m_risk_adj": 0.002327,
      "avg_1m_risk_adj_delta": 0.0014719999999999998,
      "baseline_avg_1m_mdd_proxy": -0.031865,
      "avg_1m_mdd_proxy_delta": -0.0008529999999999996,
      "baseline_worst_1m_ret": -0.076366,
      "worst_1m_ret_delta": 0.0015310000000000046,
      "baseline_compounded_validation_return": 0.54758,
      "compounded_validation_return_delta": 0.06806600000000007
    },
    {
      "policy": "baseline_top3_role",
      "periods": 26,
      "priced_periods": 26,
      "avg_1m_ret": 0.018259,
      "median_1m_ret": 0.007441,
      "win_rate": 0.576923,
      "avg_1m_risk_adj": 0.002327,
      "avg_1m_mdd_proxy": -0.031865,
      "worst_1m_ret": -0.076366,
      "compounded_validation_return": 0.54758,
      "baseline_avg_1m_ret": 0.018259,
      "avg_1m_ret_delta": 0.0,
      "baseline_win_rate": 0.576923,
      "win_rate_delta": 0.0,
      "baseline_avg_1m_risk_adj": 0.002327,
      "avg_1m_risk_adj_delta": 0.0,
      "baseline_avg_1m_mdd_proxy": -0.031865,
      "avg_1m_mdd_proxy_delta": 0.0,
      "baseline_worst_1m_ret": -0.076366,
      "worst_1m_ret_delta": 0.0,
      "baseline_compounded_validation_return": 0.54758,
      "compounded_validation_return_delta": 0.0
    },
    {
      "policy": "wf_tail_role_policy",
      "periods": 26,
      "priced_periods": 26,
      "avg_1m_ret": 0.015794,
      "median_1m_ret": 0.005359,
      "win_rate": 0.538462,
      "avg_1m_risk_adj": -0.000991,
      "avg_1m_mdd_proxy": -0.033571,
      "worst_1m_ret": -0.072504,
      "compounded_validation_return": 0.46097,
      "baseline_avg_1m_ret": 0.018259,
      "avg_1m_ret_delta": -0.002465000000000002,
      "baseline_win_rate": 0.576923,
      "win_rate_delta": -0.03846099999999997,
      "baseline_avg_1m_risk_adj": 0.002327,
      "avg_1m_risk_adj_delta": -0.0033179999999999998,
      "baseline_avg_1m_mdd_proxy": -0.031865,
      "avg_1m_mdd_proxy_delta": -0.0017059999999999992,
      "baseline_worst_1m_ret": -0.076366,
      "worst_1m_ret_delta": 0.0038620000000000043,
      "baseline_compounded_validation_return": 0.54758,
      "compounded_validation_return_delta": -0.08660999999999996
    },
    {
      "policy": "wf_tail_role_asset_policy",
      "periods": 26,
      "priced_periods": 26,
      "avg_1m_ret": 0.014266,
      "median_1m_ret": 0.004469,
      "win_rate": 0.576923,
      "avg_1m_risk_adj": -0.001357,
      "avg_1m_mdd_proxy": -0.031245,
      "worst_1m_ret": -0.025772,
      "compounded_validation_return": 0.423385,
      "baseline_avg_1m_ret": 0.018259,
      "avg_1m_ret_delta": -0.003993000000000002,
      "baseline_win_rate": 0.576923,
      "win_rate_delta": 0.0,
      "baseline_avg_1m_risk_adj": 0.002327,
      "avg_1m_risk_adj_delta": -0.0036839999999999998,
      "baseline_avg_1m_mdd_proxy": -0.031865,
      "avg_1m_mdd_proxy_delta": 0.000619999999999999,
      "baseline_worst_1m_ret": -0.076366,
      "worst_1m_ret_delta": 0.050594,
      "baseline_compounded_validation_return": 0.54758,
      "compounded_validation_return_delta": -0.12419499999999994
    }
  ],
  "recent_policy_maps": [
    {
      "signal_date": "2025-12-30",
      "history_start": "2024-12-30",
      "history_end": "2025-11-29",
      "history_rows": 2149,
      "role_policy_map": "{\"CASH_LIKE\": \"baseline_top3_role\", \"CORE_BETA\": \"hybrid_b70_ai30_top3_role\", \"DEFENSIVE\": \"hybrid_b50_ai50_top3_role\", \"INCOME\": \"baseline_top3_role\", \"SECTOR_THEME\": \"ai_quality_guard_top3_role\", \"STYLE_FACTOR\": \"ai_quality_guard_top3_role\"}",
      "asset_policy_map": "{\"BOND_LONG\": \"ai_quality_guard_top3_role\", \"CASH_RATE\": \"baseline_top3_role\", \"EQUITY_KR\": \"ai_top3_role\", \"EQUITY_US\": \"baseline_top3_role\"}",
      "top_tail_segments": "[{\"segment_type\": \"e_asset_bucket\", \"segment\": \"BOND_CORE\", \"policy\": \"ai_top3_role\", \"tail_control_score\": 0.8400000000000001}, {\"segment_type\": \"e_asset_bucket\", \"segment\": \"BOND_LONG\", \"policy\": \"ai_quality_guard_top3_role\", \"tail_control_score\": 0.86}, {\"segment_type\": \"e_asset_bucket\", \"segment\": \"BOND_SHORT\", \"policy\": \"baseline_top3_role\", \"tail_control_score\": 0.915}, {\"segment_type\": \"e_asset_bucket\", \"segment\": \"CASH_RATE\", \"policy\": \"baseline_top3_role\", \"tail_control_score\": 0.86}, {\"segment_type\": \"e_asset_bucket\", \"segment\": \"COMMODITY_GOLD\", \"policy\": \"hybrid_b50_ai50_top3_role\", \"tail_control_score\": 0.865}, {\"segment_type\": \"e_asset_bucket\", \"segment\": \"COMMODITY_OTHER\", \"policy\": \"baseline_top3_role\", \"tail_control_score\": 0.625}, {\"segment_type\": \"e_asset_bucket\", \"segment\": \"EQUITY_CHINA\", \"policy\": \"ai_top3_role\", \"tail_control_score\": 0.8400000000000001}, {\"segment_type\": \"e_asset_bucket\", \"segment\": \"EQUITY_GLOBAL\", \"policy\": \"ai_top3_role\", \"tail_control_score\": 0.7999999999999999}, {\"segment_type\": \"e_asset_bucket\", \"segment\": \"EQUITY_INDIA\", \"policy\": \"ai_quality_guard_top3_role\", \"tail_control_score\": 1.0}, {\"segment_type\": \"e_asset_bucket\", \"segment\": \"EQUITY_JAPAN\", \"policy\": \"ai_top3_role\", \"tail_control_score\": 0.625}, {\"segment_type\": \"e_asset_bucket\", \"segment\": \"EQUITY_KR\", \"policy\": \"ai_top3_role\", \"tail_control_score\": 0.745}, {\"segment_type\": \"e_asset_bucket\", \"segment\": \"EQUITY_US\", \"policy\": \"baseline_top3_role\", \"tail_control_score\": 0.81}, {\"segment_type\": \"e_asset_bucket\", \"segment\": \"EQUITY_VIETNAM\", \"policy\": \"baseline_top3_role\", \"tail_control_score\": 0.6666666666666666}, {\"segment_type\": \"e_asset_bucket\", \"segment\": \"FX_USD\", \"policy\": \"baseline_top3_role\", \"tail_control_score\": 1.0}, {\"segment_type\": \"e_asset_bucket\", \"segment\": \"HEDGE_INVERSE\", \"policy\": \"hybrid_b50_ai50_top3_role\", \"tail_control_score\": 0.845}, {\"segment_type\": \"e_asset_bucket\", \"segment\": \"MULTI_ASSET\", \"policy\": \"baseline_top3_role\", \"tail_control_score\": 0.9500000000000001}, {\"segment_type\": \"e_asset_bucket\", \"segment\": \"REIT_INFRA\", \"policy\": \"ai_quality_guard_top3_role\", \"tail_control_score\": 0.8833333333333333}, {\"segment_type\": \"e_series_role\", \"segment\": \"CASH_LIKE\", \"policy\": \"baseline_top3_role\", \"tail_control_score\": 0.965}, {\"segment_type\": \"e_series_role\", \"segment\": \"CORE_BETA\", \"policy\": \"hybrid_b70_ai30_top3_role\", \"tail_control_score\": 0.8200000000000001}, {\"segment_type\": \"e_series_role\", \"segment\": \"DEFENSIVE\", \"policy\": \"hybrid_b50_ai50_top3_role\", \"tail_control_score\": 0.8900000000000001}, {\"segment_type\": \"e_series_role\", \"segment\": \"INCOME\", \"policy\": \"baseline_top3_role\", \"tail_control_score\": 1.0}, {\"segment_type\": \"e_series_role\", \"segment\": \"SECTOR_THEME\", \"policy\": \"ai_quality_guard_top3_role\", \"tail_control_score\": 0.7650000000000001}, {\"segment_type\": \"e_series_role\", \"segment\": \"STYLE_FACTOR\", \"policy\": \"ai_quality_guard_top3_role\", \"tail_control_score\": 0.86}]"
    },
    {
      "signal_date": "2026-01-30",
      "history_start": "2025-01-30",
      "history_end": "2025-12-30",
      "history_rows": 2203,
      "role_policy_map": "{\"CASH_LIKE\": \"baseline_top3_role\", \"CORE_BETA\": \"hybrid_b70_ai30_top3_role\", \"DEFENSIVE\": \"hybrid_b50_ai50_top3_role\", \"INCOME\": \"baseline_top3_role\", \"SECTOR_THEME\": \"ai_quality_guard_top3_role\", \"STYLE_FACTOR\": \"baseline_top3_role\"}",
      "asset_policy_map": "{\"BOND_LONG\": \"ai_quality_guard_top3_role\", \"CASH_RATE\": \"baseline_top3_role\", \"EQUITY_KR\": \"hybrid_b70_ai30_top3_role\", \"EQUITY_US\": \"baseline_top3_role\"}",
      "top_tail_segments": "[{\"segment_type\": \"e_asset_bucket\", \"segment\": \"BOND_CORE\", \"policy\": \"ai_top3_role\", \"tail_control_score\": 0.9000000000000001}, {\"segment_type\": \"e_asset_bucket\", \"segment\": \"BOND_LONG\", \"policy\": \"ai_quality_guard_top3_role\", \"tail_control_score\": 0.86}, {\"segment_type\": \"e_asset_bucket\", \"segment\": \"BOND_SHORT\", \"policy\": \"baseline_top3_role\", \"tail_control_score\": 0.915}, {\"segment_type\": \"e_asset_bucket\", \"segment\": \"CASH_RATE\", \"policy\": \"baseline_top3_role\", \"tail_control_score\": 0.8200000000000001}, {\"segment_type\": \"e_asset_bucket\", \"segment\": \"COMMODITY_GOLD\", \"policy\": \"hybrid_b50_ai50_top3_role\", \"tail_control_score\": 0.865}, {\"segment_type\": \"e_asset_bucket\", \"segment\": \"COMMODITY_OTHER\", \"policy\": \"baseline_top3_role\", \"tail_control_score\": 0.625}, {\"segment_type\": \"e_asset_bucket\", \"segment\": \"EQUITY_CHINA\", \"policy\": \"ai_top3_role\", \"tail_control_score\": 0.8900000000000001}, {\"segment_type\": \"e_asset_bucket\", \"segment\": \"EQUITY_GLOBAL\", \"policy\": \"ai_top3_role\", \"tail_control_score\": 0.7999999999999999}, {\"segment_type\": \"e_asset_bucket\", \"segment\": \"EQUITY_INDIA\", \"policy\": \"ai_quality_guard_top3_role\", \"tail_control_score\": 1.0}, {\"segment_type\": \"e_asset_bucket\", \"segment\": \"EQUITY_JAPAN\", \"policy\": \"hybrid_b70_ai30_top3_role\", \"tail_control_score\": 0.6749999999999999}, {\"segment_type\": \"e_asset_bucket\", \"segment\": \"EQUITY_KR\", \"policy\": \"hybrid_b70_ai30_top3_role\", \"tail_control_score\": 0.745}, {\"segment_type\": \"e_asset_bucket\", \"segment\": \"EQUITY_US\", \"policy\": \"baseline_top3_role\", \"tail_control_score\": 0.8400000000000001}, {\"segment_type\": \"e_asset_bucket\", \"segment\": \"EQUITY_VIETNAM\", \"policy\": \"baseline_top3_role\", \"tail_control_score\": 0.6666666666666666}, {\"segment_type\": \"e_asset_bucket\", \"segment\": \"FX_USD\", \"policy\": \"baseline_top3_role\", \"tail_control_score\": 1.0}, {\"segment_type\": \"e_asset_bucket\", \"segment\": \"HEDGE_INVERSE\", \"policy\": \"hybrid_b50_ai50_top3_role\", \"tail_control_score\": 0.8687499999999999}, {\"segment_type\": \"e_asset_bucket\", \"segment\": \"MULTI_ASSET\", \"policy\": \"baseline_top3_role\", \"tail_control_score\": 1.0}, {\"segment_type\": \"e_asset_bucket\", \"segment\": \"REIT_INFRA\", \"policy\": \"ai_quality_guard_top3_role\", \"tail_control_score\": 0.8833333333333333}, {\"segment_type\": \"e_series_role\", \"segment\": \"CASH_LIKE\", \"policy\": \"baseline_top3_role\", \"tail_control_score\": 0.965}, {\"segment_type\": \"e_series_role\", \"segment\": \"CORE_BETA\", \"policy\": \"hybrid_b70_ai30_top3_role\", \"tail_control_score\": 0.8300000000000001}, {\"segment_type\": \"e_series_role\", \"segment\": \"DEFENSIVE\", \"policy\": \"hybrid_b50_ai50_top3_role\", \"tail_control_score\": 0.9}, {\"segment_type\": \"e_series_role\", \"segment\": \"INCOME\", \"policy\": \"baseline_top3_role\", \"tail_control_score\": 1.0}, {\"segment_type\": \"e_series_role\", \"segment\": \"SECTOR_THEME\", \"policy\": \"ai_quality_guard_top3_role\", \"tail_control_score\": 0.7550000000000001}, {\"segment_type\": \"e_series_role\", \"segment\": \"STYLE_FACTOR\", \"policy\": \"baseline_top3_role\", \"tail_control_score\": 0.84}]"
    },
    {
      "signal_date": "2026-02-27",
      "history_start": "2025-02-27",
      "history_end": "2026-01-27",
      "history_rows": 2048,
      "role_policy_map": "{\"CASH_LIKE\": \"baseline_top3_role\", \"CORE_BETA\": \"hybrid_b70_ai30_top3_role\", \"DEFENSIVE\": \"hybrid_b70_ai30_top3_role\", \"INCOME\": \"baseline_top3_role\", \"SECTOR_THEME\": \"ai_quality_guard_top3_role\", \"STYLE_FACTOR\": \"baseline_top3_role\"}",
      "asset_policy_map": "{\"BOND_LONG\": \"ai_quality_guard_top3_role\", \"CASH_RATE\": \"baseline_top3_role\", \"EQUITY_KR\": \"ai_top3_role\", \"EQUITY_US\": \"baseline_top3_role\"}",
      "top_tail_segments": "[{\"segment_type\": \"e_asset_bucket\", \"segment\": \"BOND_CORE\", \"policy\": \"ai_top3_role\", \"tail_control_score\": 0.9100000000000001}, {\"segment_type\": \"e_asset_bucket\", \"segment\": \"BOND_LONG\", \"policy\": \"ai_top3_role\", \"tail_control_score\": 0.8600000000000001}, {\"segment_type\": \"e_asset_bucket\", \"segment\": \"BOND_SHORT\", \"policy\": \"baseline_top3_role\", \"tail_control_score\": 0.915}, {\"segment_type\": \"e_asset_bucket\", \"segment\": \"CASH_RATE\", \"policy\": \"baseline_top3_role\", \"tail_control_score\": 0.8200000000000001}, {\"segment_type\": \"e_asset_bucket\", \"segment\": \"COMMODITY_GOLD\", \"policy\": \"hybrid_b50_ai50_top3_role\", \"tail_control_score\": 0.865}, {\"segment_type\": \"e_asset_bucket\", \"segment\": \"COMMODITY_OTHER\", \"policy\": \"baseline_top3_role\", \"tail_control_score\": 0.625}, {\"segment_type\": \"e_asset_bucket\", \"segment\": \"EQUITY_CHINA\", \"policy\": \"ai_top3_role\", \"tail_control_score\": 0.96}, {\"segment_type\": \"e_asset_bucket\", \"segment\": \"EQUITY_GLOBAL\", \"policy\": \"ai_top3_role\", \"tail_control_score\": 0.86}, {\"segment_type\": \"e_asset_bucket\", \"segment\": \"EQUITY_INDIA\", \"policy\": \"ai_quality_guard_top3_role\", \"tail_control_score\": 1.0}, {\"segment_type\": \"e_asset_bucket\", \"segment\": \"EQUITY_JAPAN\", \"policy\": \"hybrid_b70_ai30_top3_role\", \"tail_control_score\": 0.6749999999999999}, {\"segment_type\": \"e_asset_bucket\", \"segment\": \"EQUITY_KR\", \"policy\": \"ai_top3_role\", \"tail_control_score\": 0.695}, {\"segment_type\": \"e_asset_bucket\", \"segment\": \"EQUITY_US\", \"policy\": \"baseline_top3_role\", \"tail_control_score\": 0.8400000000000001}, {\"segment_type\": \"e_asset_bucket\", \"segment\": \"EQUITY_VIETNAM\", \"policy\": \"baseline_top3_role\", \"tail_control_score\": 0.6666666666666666}, {\"segment_type\": \"e_asset_bucket\", \"segment\": \"FX_USD\", \"policy\": \"ai_top3_role\", \"tail_control_score\": 0.7499999999999999}, {\"segment_type\": \"e_asset_bucket\", \"segment\": \"HEDGE_INVERSE\", \"policy\": \"hybrid_b50_ai50_top3_role\", \"tail_control_score\": 0.8687499999999999}, {\"segment_type\": \"e_asset_bucket\", \"segment\": \"MULTI_ASSET\", \"policy\": \"baseline_top3_role\", \"tail_control_score\": 0.9450000000000001}, {\"segment_type\": \"e_asset_bucket\", \"segment\": \"REIT_INFRA\", \"policy\": \"ai_quality_guard_top3_role\", \"tail_control_score\": 0.8833333333333333}, {\"segment_type\": \"e_series_role\", \"segment\": \"CASH_LIKE\", \"policy\": \"baseline_top3_role\", \"tail_control_score\": 0.965}, {\"segment_type\": \"e_series_role\", \"segment\": \"CORE_BETA\", \"policy\": \"hybrid_b70_ai30_top3_role\", \"tail_control_score\": 0.8400000000000001}, {\"segment_type\": \"e_series_role\", \"segment\": \"DEFENSIVE\", \"policy\": \"hybrid_b70_ai30_top3_role\", \"tail_control_score\": 0.8099999999999999}, {\"segment_type\": \"e_series_role\", \"segment\": \"INCOME\", \"policy\": \"baseline_top3_role\", \"tail_control_score\": 0.965}, {\"segment_type\": \"e_series_role\", \"segment\": \"SECTOR_THEME\", \"policy\": \"ai_quality_guard_top3_role\", \"tail_control_score\": 0.7550000000000001}, {\"segment_type\": \"e_series_role\", \"segment\": \"STYLE_FACTOR\", \"policy\": \"baseline_top3_role\", \"tail_control_score\": 0.84}]"
    },
    {
      "signal_date": "2026-03-31",
      "history_start": "2025-03-31",
      "history_end": "2026-02-28",
      "history_rows": 2277,
      "role_policy_map": "{\"CASH_LIKE\": \"baseline_top3_role\", \"CORE_BETA\": \"ai_quality_guard_top3_role\", \"DEFENSIVE\": \"hybrid_b70_ai30_top3_role\", \"INCOME\": \"baseline_top3_role\", \"SECTOR_THEME\": \"ai_top3_role\", \"STYLE_FACTOR\": \"ai_quality_guard_top3_role\"}",
      "asset_policy_map": "{\"BOND_LONG\": \"ai_quality_guard_top3_role\", \"CASH_RATE\": \"ai_quality_guard_top3_role\", \"EQUITY_KR\": \"ai_quality_guard_top3_role\", \"EQUITY_US\": \"ai_quality_guard_top3_role\"}",
      "top_tail_segments": "[{\"segment_type\": \"e_asset_bucket\", \"segment\": \"BOND_CORE\", \"policy\": \"ai_top3_role\", \"tail_control_score\": 0.97}, {\"segment_type\": \"e_asset_bucket\", \"segment\": \"BOND_LONG\", \"policy\": \"ai_top3_role\", \"tail_control_score\": 0.87}, {\"segment_type\": \"e_asset_bucket\", \"segment\": \"BOND_SHORT\", \"policy\": \"baseline_top3_role\", \"tail_control_score\": 0.8949999999999999}, {\"segment_type\": \"e_asset_bucket\", \"segment\": \"CASH_RATE\", \"policy\": \"ai_quality_guard_top3_role\", \"tail_control_score\": 0.7500000000000001}, {\"segment_type\": \"e_asset_bucket\", \"segment\": \"COMMODITY_GOLD\", \"policy\": \"ai_top3_role\", \"tail_control_score\": 0.8949999999999999}, {\"segment_type\": \"e_asset_bucket\", \"segment\": \"COMMODITY_OTHER\", \"policy\": \"baseline_top3_role\", \"tail_control_score\": 0.625}, {\"segment_type\": \"e_asset_bucket\", \"segment\": \"EQUITY_CHINA\", \"policy\": \"ai_top3_role\", \"tail_control_score\": 0.96}, {\"segment_type\": \"e_asset_bucket\", \"segment\": \"EQUITY_GLOBAL\", \"policy\": \"ai_top3_role\", \"tail_control_score\": 0.86}, {\"segment_type\": \"e_asset_bucket\", \"segment\": \"EQUITY_INDIA\", \"policy\": \"ai_quality_guard_top3_role\", \"tail_control_score\": 1.0}, {\"segment_type\": \"e_asset_bucket\", \"segment\": \"EQUITY_JAPAN\", \"policy\": \"ai_top3_role\", \"tail_control_score\": 1.0}, {\"segment_type\": \"e_asset_bucket\", \"segment\": \"EQUITY_KR\", \"policy\": \"ai_quality_guard_top3_role\", \"tail_control_score\": 1.0}, {\"segment_type\": \"e_asset_bucket\", \"segment\": \"EQUITY_US\", \"policy\": \"hybrid_b50_ai50_top3_role\", \"tail_control_score\": 0.795}, {\"segment_type\": \"e_asset_bucket\", \"segment\": \"EQUITY_VIETNAM\", \"policy\": \"baseline_top3_role\", \"tail_control_score\": 0.6666666666666666}, {\"segment_type\": \"e_asset_bucket\", \"segment\": \"FX_USD\", \"policy\": \"ai_top3_role\", \"tail_control_score\": 0.7499999999999999}, {\"segment_type\": \"e_asset_bucket\", \"segment\": \"HEDGE_INVERSE\", \"policy\": \"hybrid_b50_ai50_top3_role\", \"tail_control_score\": 0.85625}, {\"segment_type\": \"e_asset_bucket\", \"segment\": \"MULTI_ASSET\", \"policy\": \"ai_quality_guard_top3_role\", \"tail_control_score\": 1.0}, {\"segment_type\": \"e_asset_bucket\", \"segment\": \"REIT_INFRA\", \"policy\": \"hybrid_b70_ai30_top3_role\", \"tail_control_score\": 0.7000000000000001}, {\"segment_type\": \"e_series_role\", \"segment\": \"CASH_LIKE\", \"policy\": \"baseline_top3_role\", \"tail_control_score\": 0.9349999999999999}, {\"segment_type\": \"e_series_role\", \"segment\": \"CORE_BETA\", \"policy\": \"ai_quality_guard_top3_role\", \"tail_control_score\": 0.68}, {\"segment_type\": \"e_series_role\", \"segment\": \"DEFENSIVE\", \"policy\": \"hybrid_b70_ai30_top3_role\", \"tail_control_score\": 0.8099999999999999}, {\"segment_type\": \"e_series_role\", \"segment\": \"INCOME\", \"policy\": \"baseline_top3_role\", \"tail_control_score\": 0.775}, {\"segment_type\": \"e_series_role\", \"segment\": \"SECTOR_THEME\", \"policy\": \"ai_top3_role\", \"tail_control_score\": 1.0}, {\"segment_type\": \"e_series_role\", \"segment\": \"STYLE_FACTOR\", \"policy\": \"ai_quality_guard_top3_role\", \"tail_control_score\": 0.9}]"
    },
    {
      "signal_date": "2026-05-13",
      "history_start": "2025-05-13",
      "history_end": "2026-04-12",
      "history_rows": 2164,
      "role_policy_map": "{\"CASH_LIKE\": \"baseline_top3_role\", \"CORE_BETA\": \"ai_quality_guard_top3_role\", \"DEFENSIVE\": \"hybrid_b70_ai30_top3_role\", \"INCOME\": \"ai_quality_guard_top3_role\", \"SECTOR_THEME\": \"ai_top3_role\", \"STYLE_FACTOR\": \"ai_quality_guard_top3_role\"}",
      "asset_policy_map": "{\"CASH_RATE\": \"baseline_top3_role\", \"EQUITY_KR\": \"ai_quality_guard_top3_role\", \"EQUITY_US\": \"ai_quality_guard_top3_role\"}",
      "top_tail_segments": "[{\"segment_type\": \"e_asset_bucket\", \"segment\": \"BOND_CORE\", \"policy\": \"ai_top3_role\", \"tail_control_score\": 0.97}, {\"segment_type\": \"e_asset_bucket\", \"segment\": \"BOND_LONG\", \"policy\": \"hybrid_b70_ai30_top3_role\", \"tail_control_score\": 1.0}, {\"segment_type\": \"e_asset_bucket\", \"segment\": \"BOND_SHORT\", \"policy\": \"ai_top3_role\", \"tail_control_score\": 0.77}, {\"segment_type\": \"e_asset_bucket\", \"segment\": \"CASH_RATE\", \"policy\": \"baseline_top3_role\", \"tail_control_score\": 0.74}, {\"segment_type\": \"e_asset_bucket\", \"segment\": \"COMMODITY_GOLD\", \"policy\": \"ai_top3_role\", \"tail_control_score\": 0.9249999999999999}, {\"segment_type\": \"e_asset_bucket\", \"segment\": \"COMMODITY_OTHER\", \"policy\": \"ai_top3_role\", \"tail_control_score\": 1.0}, {\"segment_type\": \"e_asset_bucket\", \"segment\": \"EQUITY_CHINA\", \"policy\": \"ai_top3_role\", \"tail_control_score\": 0.9625}, {\"segment_type\": \"e_asset_bucket\", \"segment\": \"EQUITY_GLOBAL\", \"policy\": \"ai_top3_role\", \"tail_control_score\": 0.86875}, {\"segment_type\": \"e_asset_bucket\", \"segment\": \"EQUITY_INDIA\", \"policy\": \"ai_quality_guard_top3_role\", \"tail_control_score\": 1.0}, {\"segment_type\": \"e_asset_bucket\", \"segment\": \"EQUITY_JAPAN\", \"policy\": \"ai_top3_role\", \"tail_control_score\": 1.0}, {\"segment_type\": \"e_asset_bucket\", \"segment\": \"EQUITY_KR\", \"policy\": \"ai_quality_guard_top3_role\", \"tail_control_score\": 0.99}, {\"segment_type\": \"e_asset_bucket\", \"segment\": \"EQUITY_US\", \"policy\": \"ai_quality_guard_top3_role\", \"tail_control_score\": 1.0}, {\"segment_type\": \"e_asset_bucket\", \"segment\": \"EQUITY_VIETNAM\", \"policy\": \"baseline_top3_role\", \"tail_control_score\": 0.6666666666666666}, {\"segment_type\": \"e_asset_bucket\", \"segment\": \"FX_USD\", \"policy\": \"ai_top3_role\", \"tail_control_score\": 0.8333333333333334}, {\"segment_type\": \"e_asset_bucket\", \"segment\": \"HEDGE_INVERSE\", \"policy\": \"hybrid_b50_ai50_top3_role\", \"tail_control_score\": 0.84375}, {\"segment_type\": \"e_asset_bucket\", \"segment\": \"MULTI_ASSET\", \"policy\": \"ai_quality_guard_top3_role\", \"tail_control_score\": 0.89}, {\"segment_type\": \"e_asset_bucket\", \"segment\": \"REIT_INFRA\", \"policy\": \"ai_quality_guard_top3_role\", \"tail_control_score\": 1.0}, {\"segment_type\": \"e_series_role\", \"segment\": \"CASH_LIKE\", \"policy\": \"baseline_top3_role\", \"tail_control_score\": 0.7799999999999999}, {\"segment_type\": \"e_series_role\", \"segment\": \"CORE_BETA\", \"policy\": \"ai_quality_guard_top3_role\", \"tail_control_score\": 0.7100000000000001}, {\"segment_type\": \"e_series_role\", \"segment\": \"DEFENSIVE\", \"policy\": \"hybrid_b70_ai30_top3_role\", \"tail_control_score\": 0.87}, {\"segment_type\": \"e_series_role\", \"segment\": \"INCOME\", \"policy\": \"ai_quality_guard_top3_role\", \"tail_control_score\": 0.75}, {\"segment_type\": \"e_series_role\", \"segment\": \"SECTOR_THEME\", \"policy\": \"ai_top3_role\", \"tail_control_score\": 0.9200000000000002}, {\"segment_type\": \"e_series_role\", \"segment\": \"STYLE_FACTOR\", \"policy\": \"ai_quality_guard_top3_role\", \"tail_control_score\": 0.88}]"
    }
  ],
  "outputs": {
    "selected_csv": "D:\\Quant\\reports\\e_series_etf\\e_series_etf_tail_risk_policy_walk_forward_selected_20260513.csv",
    "periods_csv": "D:\\Quant\\reports\\e_series_etf\\e_series_etf_tail_risk_policy_walk_forward_periods_20260513.csv",
    "summary_csv": "D:\\Quant\\reports\\e_series_etf\\e_series_etf_tail_risk_policy_walk_forward_summary_20260513.csv",
    "maps_csv": "D:\\Quant\\reports\\e_series_etf\\e_series_etf_tail_risk_policy_walk_forward_maps_20260513.csv",
    "json": "D:\\Quant\\reports\\e_series_etf\\e_series_etf_tail_risk_policy_walk_forward_20260513.json",
    "markdown": "D:\\Quant\\reports\\e_series_etf\\e_series_etf_tail_risk_policy_walk_forward_20260513.md",
    "admin_current_json": "D:\\Quant\\service_platform\\web\\admin_data\\current\\e_series_etf_tail_risk_policy_walk_forward_current.json"
  }
}